webmention_tools-0.4.1.data/data/LICENSE.txt
webmention_tools-0.4.1.data/scripts/webmention-tools
webmentiontools/.__init__.py.swp
webmentiontools/__init__.py
webmentiontools/send.py
webmentiontools/urlinfo.py
webmentiontools/webmentionio.py
webmention_tools-0.4.1.dist-info/LICENSE.txt
webmention_tools-0.4.1.dist-info/METADATA
webmention_tools-0.4.1.dist-info/WHEEL
webmention_tools-0.4.1.dist-info/top_level.txt
webmention_tools-0.4.1.dist-info/RECORD
