Metadata-Version: 2.1
Name: webmention-tools
Version: 0.4.1
Summary: Tools for webmention.org.
Home-page: https://github.com/Ryuno-Ki/webmention-tools
Author: Panayotis Vryonis
Author-email: vrypan@gmail.com
Maintainer: André Jaenisch
Maintainer-email: andre.jaenisch@posteo.de
License: MIT
Keywords: webmention
Platform: Linux
Classifier: Development Status :: 1 - Planning
Classifier: Environment :: Console
Classifier: Intended Audience :: Developers
Classifier: License :: OSI Approved :: MIT License
Classifier: Operating System :: POSIX :: Linux
Classifier: Programming Language :: Python :: 3.6
Classifier: Programming Language :: Python :: 3.7
Classifier: Topic :: Internet :: WWW/HTTP
Requires-Dist: beautifulsoup4
Requires-Dist: requests
Requires-Dist: docopt
